link_sweep/__init__.py
link_sweep/cli.py
link_sweep/link_checker.py
link_sweep/markdown_parser.py
link_sweep-0.1.1.dist-info/METADATA
link_sweep-0.1.1.dist-info/WHEEL
link_sweep-0.1.1.dist-info/entry_points.txt
link_sweep-0.1.1.dist-info/licenses/LICENSE
link_sweep-0.1.1.dist-info/RECORD
