Metadata-Version: 2.4
Name: link-sweep
Version: 0.1.1
Summary: A tool for checking and cleaning dead links in Markdown files for SSGs
Project-URL: Repository, https://github.com/m0ddr/link-sweep
Project-URL: Issues, https://github.com/m0ddr/link-sweep/issues
Project-URL: Documentation, https://github.com/m0ddr/link-sweep#readme
Author: Kieran (Modder)
License: MIT
License-File: LICENSE
Keywords: ci-cd,hugo,jekyll,link-checker,links,markdown,static-site-generator,zola
Classifier: Development Status :: 4 - Beta
Classifier: Environment :: Console
Classifier: Intended Audience :: Developers
Classifier: License :: OSI Approved :: MIT License
Classifier: Operating System :: OS Independent
Classifier: Programming Language :: Python :: 3
Classifier: Programming Language :: Python :: 3.8
Classifier: Programming Language :: Python :: 3.9
Classifier: Programming Language :: Python :: 3.10
Classifier: Programming Language :: Python :: 3.11
Classifier: Programming Language :: Python :: 3.12
Classifier: Topic :: Documentation
Classifier: Topic :: Software Development :: Documentation
Classifier: Topic :: Text Processing :: Markup :: Markdown
Classifier: Topic :: Utilities
Requires-Python: >=3.8
Requires-Dist: click>=8.0.0
Requires-Dist: httpx>=0.24.0
Provides-Extra: dev
Requires-Dist: mypy>=1.0.0; extra == 'dev'
Requires-Dist: pytest-asyncio>=0.21.0; extra == 'dev'
Requires-Dist: pytest>=7.0.0; extra == 'dev'
Requires-Dist: ruff>=0.1.0; extra == 'dev'
